DDCO/Simple_Circuit/simple_circuit2.v
module simple2
(A, B, C, D);
output D;
input A,B,C;
wire w1;
and G1(w1,B,C);
or G2(D, w1, A);
endmodule

DDCO/Simple_Circuit/simple_circuit2_tb.v
module simple2_test;

reg A, B, C;
wire D;
simple2 M1(A,B,C,D);

    initial
    begin
        A=1'b0;B=1'b0;C=1'b0;
        #20;
        A=1'b0;B=1'b0;C=1'b1;
        #20;
        A=1'b0;B=1'b1;C=1'b0;
        #20;
        A=1'b0;B=1'b1;C=1'b1;
        #20;
        A=1'b1;B=1'b0;C=1'b0;
        #20;
        A=1'b1;B=1'b0;C=1'b1;
        #20;
        A=1'b1;B=1'b1;C=1'b0;
        #20;
        A=1'b1;B=1'b1;C=1'b1;
        #20;
    end

    initial
    begin
        $monitor($time," A=%b,B=%b,C=%b,D=%b",A,B,C,D);
    end

    initial
    begin
        $dumpfile("simple2.vcd");
        $dumpvars(0,simple2_test);
    end

endmodule

DDCO/Simple_Circuit/simple2.vcd
$date
	Fri Aug 25 09:44:18 2023
$end
$version
	Icarus Verilog
$end
$timescale
	1s
$end
$scope module simple2_test $end
$var wire 1 ! D $end
$var reg 1 " A $end
$var reg 1 # B $end
$var reg 1 $ C $end
$scope module M1 $end
$var wire 1 % A $end
$var wire 1 & B $end
$var wire 1 ' C $end
$var wire 1 ! D $end
$var wire 1 ( w1 $end
$upscope $end
$upscope $end
$enddefinitions $end
#0
$dumpvars
0(
0'
0&
0%
0$
0#
0"
0!
$end
#20
1$
1'
#40
0$
0'
1#
1&
#60
1!
1(
1$
1'
#80
0(
0$
0'
0#
0&
1"
1%
#100
1$
1'
#120
0$
0'
1#
1&
#140
1(
1$
1'
